klein_mongo/__init__.py
klein_mongo/connect.py
klein_mongo-3.0.0.dist-info/LICENSE.txt
klein_mongo-3.0.0.dist-info/METADATA
klein_mongo-3.0.0.dist-info/WHEEL
klein_mongo-3.0.0.dist-info/top_level.txt
klein_mongo-3.0.0.dist-info/zip-safe
klein_mongo-3.0.0.dist-info/RECORD
