Metadata-Version: 2.1
Name: klein_mongo
Version: 3.0.0
Summary: MongoDB integration
Home-page: https://github.com/mdcatapult/py-mongo
Author: Medicines Discovery Catapult
Author-email: SoftwareEngineering@md.catapult.org.uk
License: Apache V2
License-File: LICENSE.txt
Requires-Dist: klein-config >=3.0.0
Requires-Dist: pymongo[srv] >=4.4.1
